LICENSE
README.md
setup.py
eventregistry/Analytics.py
eventregistry/Base.py
eventregistry/Counts.py
eventregistry/DailyShares.py
eventregistry/EventForText.py
eventregistry/EventRegistry.py
eventregistry/Info.py
eventregistry/Logger.py
eventregistry/Query.py
eventregistry/QueryArticle.py
eventregistry/QueryArticles.py
eventregistry/QueryEvent.py
eventregistry/QueryEvents.py
eventregistry/QueryMentions.py
eventregistry/QueryStory.py
eventregistry/Recent.py
eventregistry/ReturnInfo.py
eventregistry/TopicPage.py
eventregistry/Trends.py
eventregistry/__init__.py
eventregistry/_version.py
eventregistry.egg-info/PKG-INFO
eventregistry.egg-info/SOURCES.txt
eventregistry.egg-info/dependency_links.txt
eventregistry.egg-info/not-zip-safe
eventregistry.egg-info/requires.txt
eventregistry.egg-info/top_level.txt