Metadata-Version: 2.1
Name: eventregistry
Version: 9.0
Summary: A package that can be used to query information in Event Registry (http://eventregistry.org/)
Home-page: https://github.com/EventRegistry/event-registry-python
Author: Gregor Leban
Author-email: gregor@eventregistry.org
License: MIT
Classifier: Development Status :: 4 - Beta
Classifier: License :: OSI Approved :: MIT License
Classifier: Programming Language :: Python :: 2.7
Classifier: Topic :: Text Processing :: General
Classifier: Topic :: Scientific/Engineering :: Information Analysis
Classifier: Topic :: Internet :: WWW/HTTP :: Indexing/Search
Classifier: Intended Audience :: Information Technology
License-File: LICENSE
